dlt/__init__.py
dlt/__main__.py
dlt/__plugins__.py
dlt/py.typed
dlt/version.py
dlt/_workspace/__init__.py
dlt/_workspace/_plugins.py
dlt/_workspace/_workspace_context.py
dlt/_workspace/configuration.py
dlt/_workspace/exceptions.py
dlt/_workspace/profile.py
dlt/_workspace/providers.py
dlt/_workspace/run_context.py
dlt/_workspace/_templates/_core_source_templates/__init__.py
dlt/_workspace/_templates/_core_source_templates/filesystem_pipeline.py
dlt/_workspace/_templates/_core_source_templates/rest_api_pipeline.py
dlt/_workspace/_templates/_core_source_templates/sql_database_pipeline.py
dlt/_workspace/_templates/_single_file_templates/.gitignore
dlt/_workspace/_templates/_single_file_templates/__init__.py
dlt/_workspace/_templates/_single_file_templates/arrow_pipeline.py
dlt/_workspace/_templates/_single_file_templates/dataframe_pipeline.py
dlt/_workspace/_templates/_single_file_templates/debug_pipeline.py
dlt/_workspace/_templates/_single_file_templates/default_pipeline.py
dlt/_workspace/_templates/_single_file_templates/fruitshop_pipeline.py
dlt/_workspace/_templates/_single_file_templates/github_api_pipeline.py
dlt/_workspace/_templates/_single_file_templates/requests_pipeline.py
dlt/_workspace/_templates/_single_file_templates/vibe_rest_api_pipeline.py
dlt/_workspace/_templates/_single_file_templates/.dlt/config.toml
dlt/_workspace/cli/__init__.py
dlt/_workspace/cli/_ai_command.py
dlt/_workspace/cli/_debug.py
dlt/_workspace/cli/_deploy_command.py
dlt/_workspace/cli/_deploy_command_helpers.py
dlt/_workspace/cli/_dlt.py
dlt/_workspace/cli/_docs_command.py
dlt/_workspace/cli/_init_command.py
dlt/_workspace/cli/_pipeline_command.py
dlt/_workspace/cli/_pipeline_files.py
dlt/_workspace/cli/_plugins.py
dlt/_workspace/cli/_profile_command.py
dlt/_workspace/cli/_telemetry_command.py
dlt/_workspace/cli/_workspace_command.py
dlt/_workspace/cli/commands.py
dlt/_workspace/cli/config_toml_writer.py
dlt/_workspace/cli/echo.py
dlt/_workspace/cli/exceptions.py
dlt-1.21.0.dist-info/METADATA
dlt-1.21.0.dist-info/WHEEL
dlt-1.21.0.dist-info/entry_points.txt
dlt-1.21.0.dist-info/licenses/LICENSE.txt
dlt-1.21.0.dist-info/RECORD
