Metadata-Version: 2.4
Name: dlt
Version: 1.21.0
Summary: dlt is an open-source python-first scalable data loading library that does not require any backend to run.
Project-URL: Homepage, https://github.com/dlt-hub
Project-URL: Repository, https://github.com/dlt-hub/dlt
Author-email: "dltHub Inc." <services@dlthub.com>
Maintainer-email: Marcin Rudolf <marcin@dlthub.com>, Adrian Brudaru <adrian@dlthub.com>, Anton Burnashev <anton@dlthub.com>, David Scharf <david@dlthub.com>
License-Expression: Apache-2.0
License-File: LICENSE.txt
Keywords: etl
Classifier: Development Status :: 5 - Production/Stable
Classifier: Intended Audience :: Developers
Classifier: License :: OSI Approved :: Apache Software License
Classifier: Operating System :: MacOS :: MacOS X
Classifier: Operating System :: Microsoft :: Windows
Classifier: Operating System :: POSIX :: Linux
Classifier: Programming Language :: Python :: 3.9
Classifier: Programming Language :: Python :: 3.10
Classifier: Programming Language :: Python :: 3.11
Classifier: Programming Language :: Python :: 3.12
Classifier: Programming Language :: Python :: 3.13
Classifier: Topic :: Software Development :: Libraries
Classifier: Typing :: Typed
Requires-Python: <3.15,>=3.9.2
Requires-Dist: click>=7.1
Requires-Dist: fsspec>=2022.4.0
Requires-Dist: gitpython>=3.1.29
Requires-Dist: giturlparse>=0.10.0
Requires-Dist: humanize>=4.4.0
Requires-Dist: jsonpath-ng>=1.5.3
Requires-Dist: orjson!=3.10.1,!=3.9.11,!=3.9.12,!=3.9.13,!=3.9.14,<4,>=3.6.7; platform_python_implementation != 'PyPy' and sys_platform != 'emscripten'
Requires-Dist: orjson>=3.10.1; platform_python_implementation != 'PyPy' and sys_platform != 'emscripten'
Requires-Dist: orjson>=3.11.0; python_version > '3.13'
Requires-Dist: packaging>=21.1
Requires-Dist: pathvalidate>=2.5.2
Requires-Dist: pendulum>=2.1.2
Requires-Dist: pendulum>=3.0.0; python_version > '3.13'
Requires-Dist: pluggy>=1.3.0
Requires-Dist: pytz>=2022.6
Requires-Dist: pywin32>=306; sys_platform == 'win32'
Requires-Dist: pyyaml>=5.4.1
Requires-Dist: requests>=2.26.0
Requires-Dist: requirements-parser>=0.5.0
Requires-Dist: rich-argparse>=1.6.0
Requires-Dist: semver>=3.0.0
Requires-Dist: setuptools>=65.6.0
Requires-Dist: simplejson>=3.17.5
Requires-Dist: sqlglot!=28.1,>=25.4.0
Requires-Dist: tenacity>=8.0.2
Requires-Dist: tomlkit>=0.11.3
Requires-Dist: typing-extensions>=4.8.0
Requires-Dist: tzdata>=2022.1
Requires-Dist: win-precise-time>=1.4.2; os_name == 'nt' and python_version < '3.13'
Provides-Extra: athena
Requires-Dist: botocore>=1.28; extra == 'athena'
Requires-Dist: pyarrow>=16.0.0; extra == 'athena'
Requires-Dist: pyathena>=2.9.6; extra == 'athena'
Requires-Dist: s3fs>=2022.4.0; extra == 'athena'
Provides-Extra: az
Requires-Dist: adlfs>=2024.7.0; extra == 'az'
Provides-Extra: bigquery
Requires-Dist: db-dtypes>=1.2.0; extra == 'bigquery'
Requires-Dist: gcsfs>=2022.4.0; extra == 'bigquery'
Requires-Dist: google-cloud-bigquery>=2.26.0; extra == 'bigquery'
Requires-Dist: grpcio>=1.50.0; extra == 'bigquery'
Requires-Dist: pyarrow>=16.0.0; extra == 'bigquery'
Provides-Extra: cli
Requires-Dist: cron-descriptor>=1.2.32; extra == 'cli'
Requires-Dist: pip>=23.0.0; extra == 'cli'
Requires-Dist: pipdeptree<2.10,>=2.9.3; extra == 'cli'
Provides-Extra: clickhouse
Requires-Dist: adlfs>=2024.7.0; extra == 'clickhouse'
Requires-Dist: clickhouse-connect>=0.7.7; extra == 'clickhouse'
Requires-Dist: clickhouse-driver>=0.2.7; extra == 'clickhouse'
Requires-Dist: gcsfs>=2022.4.0; extra == 'clickhouse'
Requires-Dist: pyarrow>=16.0.0; extra == 'clickhouse'
Requires-Dist: s3fs>=2022.4.0; extra == 'clickhouse'
Provides-Extra: databricks
Requires-Dist: databricks-sdk>=0.38.0; extra == 'databricks'
Requires-Dist: databricks-sql-connector>=2.9.3; (python_version <= '3.12') and extra == 'databricks'
Requires-Dist: databricks-sql-connector>=3.6.0; (python_version >= '3.13') and extra == 'databricks'
Provides-Extra: dbml
Requires-Dist: pydbml; extra == 'dbml'
Provides-Extra: deltalake
Requires-Dist: deltalake>=0.25.1; extra == 'deltalake'
Requires-Dist: pyarrow>=16.0.0; extra == 'deltalake'
Provides-Extra: dremio
Requires-Dist: pyarrow>=16.0.0; extra == 'dremio'
Provides-Extra: duckdb
Requires-Dist: duckdb>=0.9; extra == 'duckdb'
Provides-Extra: ducklake
Requires-Dist: duckdb>=1.2.0; extra == 'ducklake'
Requires-Dist: pyarrow>=16.0.0; extra == 'ducklake'
Provides-Extra: fabric
Requires-Dist: adlfs>=2024.7.0; extra == 'fabric'
Requires-Dist: pyarrow>=16.0.0; extra == 'fabric'
Requires-Dist: pyodbc>=4.0.39; extra == 'fabric'
Provides-Extra: filesystem
Requires-Dist: botocore>=1.28; extra == 'filesystem'
Requires-Dist: s3fs>=2022.4.0; extra == 'filesystem'
Provides-Extra: gcp
Requires-Dist: db-dtypes>=1.2.0; extra == 'gcp'
Requires-Dist: gcsfs>=2022.4.0; extra == 'gcp'
Requires-Dist: google-cloud-bigquery>=2.26.0; extra == 'gcp'
Requires-Dist: grpcio>=1.50.0; extra == 'gcp'
Provides-Extra: gs
Requires-Dist: gcsfs>=2022.4.0; extra == 'gs'
Provides-Extra: http
Requires-Dist: aiohttp>3.9.0; extra == 'http'
Provides-Extra: hub
Requires-Dist: dlt-runtime<0.22,>=0.20.0; (python_version >= '3.10') and extra == 'hub'
Requires-Dist: dlthub<0.22,>=0.20.0; (python_version >= '3.10') and extra == 'hub'
Provides-Extra: lancedb
Requires-Dist: duckdb>=1.4.3; extra == 'lancedb'
Requires-Dist: ibis-framework>=11.0.0; extra == 'lancedb'
Requires-Dist: lancedb>=0.22.0; extra == 'lancedb'
Requires-Dist: pyarrow>=16.0.0; extra == 'lancedb'
Provides-Extra: motherduck
Requires-Dist: duckdb>=0.9; extra == 'motherduck'
Requires-Dist: pyarrow>=16.0.0; extra == 'motherduck'
Provides-Extra: mssql
Requires-Dist: pyodbc>=4.0.39; extra == 'mssql'
Provides-Extra: oracle
Requires-Dist: oracledb>=3.4.1; extra == 'oracle'
Provides-Extra: parquet
Requires-Dist: pyarrow>=16.0.0; extra == 'parquet'
Provides-Extra: postgis
Requires-Dist: psycopg2-binary>=2.9.1; extra == 'postgis'
Provides-Extra: postgres
Requires-Dist: psycopg2-binary>=2.9.1; extra == 'postgres'
Provides-Extra: pyiceberg
Requires-Dist: pyarrow>=16.0.0; extra == 'pyiceberg'
Requires-Dist: pyiceberg-core>=0.6.0; extra == 'pyiceberg'
Requires-Dist: pyiceberg>=0.9.1; extra == 'pyiceberg'
Requires-Dist: sqlalchemy>=1.4; extra == 'pyiceberg'
Provides-Extra: qdrant
Requires-Dist: qdrant-client[fastembed]>=1.8; extra == 'qdrant'
Provides-Extra: redshift
Requires-Dist: psycopg2-binary>=2.9.1; extra == 'redshift'
Provides-Extra: s3
Requires-Dist: botocore>=1.28; extra == 's3'
Requires-Dist: s3fs>=2022.4.0; extra == 's3'
Provides-Extra: sftp
Requires-Dist: paramiko>=3.3.0; extra == 'sftp'
Provides-Extra: snowflake
Requires-Dist: snowflake-connector-python>=3.5.0; extra == 'snowflake'
Provides-Extra: sql-database
Requires-Dist: sqlalchemy>=1.4; extra == 'sql-database'
Provides-Extra: sqlalchemy
Requires-Dist: alembic>1.10.0; extra == 'sqlalchemy'
Requires-Dist: sqlalchemy>=1.4; extra == 'sqlalchemy'
Provides-Extra: synapse
Requires-Dist: adlfs>=2024.7.0; extra == 'synapse'
Requires-Dist: pyarrow>=16.0.0; extra == 'synapse'
Requires-Dist: pyodbc>=4.0.39; extra == 'synapse'
Provides-Extra: weaviate
Requires-Dist: weaviate-client<5.0.0,>=4.0.0; extra == 'weaviate'
Provides-Extra: workspace
Requires-Dist: duckdb>=0.9; extra == 'workspace'
Requires-Dist: ibis-framework>=10.5.0; (python_version >= '3.10') and extra == 'workspace'
Requires-Dist: marimo>=0.14.5; extra == 'workspace'
Requires-Dist: mcp>=1.2.1; (python_version >= '3.10') and extra == 'workspace'
Requires-Dist: pathspec>=0.11.2; extra == 'workspace'
Requires-Dist: pyarrow>=16.0.0; extra == 'workspace'
